{"name":"Struthof","strava":"2221142","acces":"","length":"","gradient":"","gain":"","pre79HighestClassification":"n/a","post79HighestClassification":"1","info":"","polyline":"oe{fHsl`k@hAKp@Df@N^Dl@@vAUj@Wn@Ir@OvA^z@d@~@`@b@LpAP|@`@f@BbAMl@WnAAvB_@jC]bAWt@Pl@rA`AnATFHA^QTEl@Bf@TNN\\h@LLd@NLJHLFVHJrApAtAd@|DZhC~@\\RPP\\j@V\\|ArAdBpAt@r@h@^RLh@b@`An@~@x@r@v@|BbBnC|BtAnAbAl@h@XzBz@VHnALz@DjAV@AABDIVq@\\oC^qAB_@A}@P}@^aAz@gBn@cAX_A\\a@DKn@sBXoAf@}@b@yALUTYb@]z@c@`@GZKPI|@y@PK^WRG~@a@X]FCh@KJKf@q@`@q@Fe@Fw@Ls@De@\\_AJ]^]BId@{APoA?mAPg@HyAVy@@i@HYHcARy@Aw@BcAAi@@qAIiB`@gDFo@l@eATy@Pe@nAiBxAwATQl@[RONWNi@@KQmCYsCGu@DcALgAE}@De@Gm@FqAFe@?i@XSd@Qd@[^AJG\\{@JCJGp@yAd@s@hAcCn@}@hA{BVm@nAmBLk@tBiC`A_Ar@[|@w@NY@S\\y@NQV_@@GCIII[IG@BFKKOc@_@TORq@j@_@JSGM?QFSZ]fAGH[BAD?AQFM?GBY\\GPG\\IBsAbAo@BYJKHYb@YA_Al@]H[?]GK?a@JOJIPKnAS^EBAA@E\\Qv@WZa@LGJMTi@HYDu@H[?[E_AHc@\\[Pg@NKFKLe@DCd@EHIh@}@Fe@Nc@Ac@_@mBIcAKUWYGQE[Oe@YeAKo@[e@Kk@Cu@D_@DI@a@DQDAHLBLAJL?C\\BFFBPC`@ZVDV?nAo@NMv@O~@IJId@QPKj@q@b@g@JYFaACq@@m@FOFcANaADy@f@aCNm@JWRoB[kCu@aDE]IOC_@i@mCC]_@{@Mq@Ok@Ym@Ic@k@mA?QFSDKZ[@SRWT_ALYHq@CMCXYVYl@Uz@STQl@Un@?rB^|BLXFXFj@JRBAKe@o@kCCURn@Nr@LRPnA?XMlCERGr@M`@_@`A]nAA`@CD]f@[Xo@bACBa@HaACa@IGDc@M[Cm@Om@KWOi@OgAOIBEDGBEAGMk@Pu@\\SF_@p@Kb@MdAOl@[t@]dAa@t@O`@s@bAUPIR]d@KJYLC@KEW[Si@Ss@SUu@m@a@m@k@q@OYDOq@_@i@u@aAe@[c@u@i@ECAg@UEO[Y[S_@Om@OOs@kAi@mAo@cAQm@Ms@@UX]R]HNNPTPHZd@p@DD\\BPHz@r@NHRDHZ~@H`@@`@Jv@G^JVB\\C\\F^GNHj@D\\F\\Gr@a@h@UT[JYXm@Nm@Jy@@_@DUJU\\]T]@g@SMS@q@P_@Tw@|@Mf@ITKFa@Ck@KM?]ISQIOOSq@Q{@k@KMe@}@Qc@EYQgCKq@KmA[kBq@gC]yDJg@Kk@GkBFcBC]TaCF]Ho@t@aA^Wv@Gb@BRLRKtAHT@RGXF\\G^MJ@rAg@f@?l@YVS~@Wf@Ut@WZCv@@lAIz@Yd@W`Aa@r@_Ab@]NS`@m@Rc@L_@LQPg@`@o@`@{@Z]JGXUPSDWTs@@_@E[eAkEKmBGg@FwACs@?]E{@QmADy@?_ABe@Fc@Je@Fu@F[@_@Xy@ZoADe@Vi@jAwAJGXIb@Ub@GJGXKd@An@If@Av@Un@o@JORg@Ps@B[Co@H}@?ONa@NmA?wCF_AJw@?g@F_@@gAN_@BYNUFSNaCAUBOAu@Q{BKYKi@GK{@_AY_@a@MGAIOWQW_A_@o@a@a@a@q@EQ[o@GSOSKYEWUc@Sk@G]KWSUGKCo@_@m@Ou@g@}A]a@s@wBYsAq@iCiAwFJ_D`@_D?MRg@ZwAn@oBT_@d@wA`A}AJKLQ^SRQ|Ak@pAWh@@h@IXGz@e@d@k@JUVcAL_@\\qBTu@Nu@n@eCb@oA~@yDb@iAfB}FdAyCtAqDx@{AZc@bB{Aj@[fAaAp@a@nC_A~C{@jGgB|D{AhA]rAk@r@c@r@_@~EmDjBaBvBgB`EyEpBeC~CsEZo@t@oArCcG`@u@lBwCnBaCNWLKV?GD@@NDl@x@Tv@JTHp@RZVdAxAlCNd@Vb@XLTP\\Ff@ZdAfBb@Z`@dAf@r@TJVP`@v@rAvAJB`@V^b@Fd@H\\XfAFHDv@L\\Z`@z@v@NJ`@NZXLx@d@v@XX`@r@z@hAj@`@LN`@p@j@v@x@|@`AtAfBvB`AzAdB~BlAnAfA`B`AhAfA~A`BxC|A~AhAbBh@p@b@`@NHZHVLPD\\v@NTDVLZd@VXVHNJHZd@b@x@hAhA~@f@h@h@r@b@f@d@NVJt@^nAXj@^h@N^X`@`@|@Nh@FLPLVb@ZTLVFDl@`B`@fBj@fA`@`AFr@Rx@?Jd@xBLv@J^Pb@Lb@LXFlAJr@X~@F^?lAMfCSdCAl@CfEPrA\\bAR`@Nl@RtAd@nELdALh@f@fBnAnDZn@p@~@dB`B\\RXTLBjAn@XJ`AL`AV|@Jn@FvA?zEJdBd@hFzC|BxBpCdCdBrAn@b@x@`@pAZVBr@@TA|@Sp@YvBsAx@e@p@k@dAgAhDcCHAj@^P@ZMf@qAPO"}